djrad/__init__.py
djrad/consts.py
djrad/decorators.py
djrad/exceptions.py
djrad/json_schema.py
djrad/types.py
djrad-1.4.0.dist-info/LICENSE
djrad-1.4.0.dist-info/METADATA
djrad-1.4.0.dist-info/WHEEL
djrad-1.4.0.dist-info/top_level.txt
djrad-1.4.0.dist-info/RECORD
