Metadata-Version: 2.1
Name: djrad
Version: 1.4.0
Summary: Decorators for JSONRPC and REST API on django
Home-page: https://github.com/amirmd76/djrad.git
Author: Divar submit team - AmirMohammad Dehghan
Author-email: dehghan@mit.edu
License: MIT
Platform: UNKNOWN
Requires-Dist: django
Requires-Dist: jsonschema (>=2.6.0)
